README.md
setup.py
py_pure_client.egg-info/PKG-INFO
py_pure_client.egg-info/SOURCES.txt
py_pure_client.egg-info/dependency_links.txt
py_pure_client.egg-info/requires.txt
py_pure_client.egg-info/top_level.txt
pypureclient/__init__.py
pypureclient/api_token_manager.py
pypureclient/exceptions.py
pypureclient/keywords.py
pypureclient/properties.py
pypureclient/responses.py
pypureclient/token_manager.py
pypureclient/flasharray/__init__.py
pypureclient/flasharray/client.py
pypureclient/flasharray/FA_2_0/__init__.py
pypureclient/flasharray/FA_2_0/api_client.py
pypureclient/flasharray/FA_2_0/client.py
pypureclient/flasharray/FA_2_0/configuration.py
pypureclient/flasharray/FA_2_0/rest.py
pypureclient/flasharray/FA_2_0/api/__init__.py
pypureclient/flasharray/FA_2_0/api/authorization_api.py
pypureclient/flasharray/FA_2_0/api/connections_api.py
pypureclient/flasharray/FA_2_0/api/host_groups_api.py
pypureclient/flasharray/FA_2_0/api/hosts_api.py
pypureclient/flasharray/FA_2_0/api/volume_snapshots_api.py
pypureclient/flasharray/FA_2_0/api/volumes_api.py
pypureclient/flasharray/FA_2_0/models/__init__.py
pypureclient/flasharray/FA_2_0/models/api_version_response.py
pypureclient/flasharray/FA_2_0/models/built_in.py
pypureclient/flasharray/FA_2_0/models/chap.py
pypureclient/flasharray/FA_2_0/models/connection.py
pypureclient/flasharray/FA_2_0/models/connection_get_response.py
pypureclient/flasharray/FA_2_0/models/connection_post.py
pypureclient/flasharray/FA_2_0/models/connection_response.py
pypureclient/flasharray/FA_2_0/models/destroyed_patch_post.py
pypureclient/flasharray/FA_2_0/models/fixed_reference.py
pypureclient/flasharray/FA_2_0/models/fixed_reference_no_id.py
pypureclient/flasharray/FA_2_0/models/host.py
pypureclient/flasharray/FA_2_0/models/host_get_response.py
pypureclient/flasharray/FA_2_0/models/host_group.py
pypureclient/flasharray/FA_2_0/models/host_group_get_response.py
pypureclient/flasharray/FA_2_0/models/host_group_patch.py
pypureclient/flasharray/FA_2_0/models/host_group_performance.py
pypureclient/flasharray/FA_2_0/models/host_group_performance_by_array.py
pypureclient/flasharray/FA_2_0/models/host_group_response.py
