Metadata-Version: 2.1
Name: py-pure-client
Version: 1.14.0
Summary: Pure Storage Python clients for FlashArray, FlashBlade, and Pure1 APIs
Home-page: https://github.com/PureStorage-OpenConnect/py-pure-client
Author: Pure Storage
Author-email: tvilcu@purestorage.com
License: BSD 2-Clause
Download-URL: https://github.com/PureStorage-OpenConnect/py-pure-client/archive/1.14.0.tar.gz
Keywords: Swagger,Pure Storage,Python,clients,REST,API,FlashArray,FlashBlade,Pure1
Platform: UNKNOWN
